middle_auth_client/__init__.py
middle_auth_client/decorators.py
middle_auth_client/ratelimit.py
middle_auth_client-3.19.0.dist-info/licenses/LICENSE
middle_auth_client-3.19.0.dist-info/METADATA
middle_auth_client-3.19.0.dist-info/WHEEL
middle_auth_client-3.19.0.dist-info/top_level.txt
middle_auth_client-3.19.0.dist-info/RECORD
