Metadata-Version: 2.4
Name: middle_auth_client
Version: 3.19.0
Summary: tools for helping web services and users interact with the middle_auth_service via flask and python
Home-page: https://github.com/seung-lab/middle_auth_client
Author: Chris Jordan
Author-email: chris@eyewire.org
License-File: LICENSE
Requires-Dist: flask
Requires-Dist: furl
Requires-Dist: requests
Requires-Dist: cachetools
Dynamic: author
Dynamic: author-email
Dynamic: home-page
Dynamic: license-file
Dynamic: requires-dist
Dynamic: summary
